price_monitor/__init__.py
price_monitor/admin.py
price_monitor/app_settings.py
price_monitor/forms.py
price_monitor/tasks.py
price_monitor/urls.py
price_monitor/utils.py
price_monitor/views.py
price_monitor/api/__init__.py
price_monitor/api/urls.py
price_monitor/api/renderers/PriceChartPNGRenderer.py
price_monitor/api/renderers/__init__.py
price_monitor/api/serializers/EmailNotificationSerializer.py
price_monitor/api/serializers/PriceSerializer.py
price_monitor/api/serializers/ProductSerializer.py
price_monitor/api/serializers/SubscriptionSerializer.py
price_monitor/api/serializers/__init__.py
price_monitor/api/views/EmailNotificationListView.py
price_monitor/api/views/PriceListView.py
price_monitor/api/views/ProductCreateRetrieveUpdateDestroyAPIView.py
price_monitor/api/views/ProductListView.py
price_monitor/api/views/SubscriptionListView.py
price_monitor/api/views/SubscriptionRetrieveView.py
price_monitor/api/views/__init__.py
price_monitor/api/views/mixins/ProductFilteringMixin.py
price_monitor/api/views/mixins/__init__.py
price_monitor/management/__init__.py
price_monitor/management/commands/__init__.py
price_monitor/management/commands/price_monitor_batch_create_products.py
price_monitor/management/commands/price_monitor_clean_db.py
price_monitor/management/commands/price_monitor_recreate_product.py
price_monitor/management/commands/price_monitor_search.py
price_monitor/migrations/0001_initial.py
price_monitor/migrations/0002_add_min_max_fk_to_product.py
price_monitor/migrations/0003_datamigration_for_min_max_cur_fks.py
price_monitor/migrations/0004_make_price_and_currency_nullable.py
price_monitor/migrations/0005_product_artist.py
price_monitor/migrations/__init__.py
price_monitor/models/EmailNotification.py
price_monitor/models/Price.py
price_monitor/models/Product.py
price_monitor/models/Subscription.py
price_monitor/models/__init__.py
price_monitor/models/mixins/PublicIDMixin.py
django_amazon_price_monitor-0.7.dist-info/top_level.txt
django_amazon_price_monitor-0.7.dist-info/METADATA
django_amazon_price_monitor-0.7.dist-info/DESCRIPTION.rst
django_amazon_price_monitor-0.7.dist-info/metadata.json
django_amazon_price_monitor-0.7.dist-info/WHEEL
django_amazon_price_monitor-0.7.dist-info/RECORD
