Metadata-Version: 2.0
Name: django-amazon-price-monitor
Version: 0.7
Summary: Monitors prices of Amazon products via Product Advertising API
Home-page: https://github.com/ponyriders/django-amazon-price-monitor
Author: Alexander Herrmann, Martin Mrose
Author-email: django-amazon-price-monitor@googlegroups.com
License: MIT
Platform: UNKNOWN
Requires-Dist: Django (>=1.8,<1.10)
Requires-Dist: beautifulsoup4
Requires-Dist: bottlenose (>=0.6.2)
Requires-Dist: celery (>=3)
Requires-Dist: python-dateutil (>=2.5.1)
Requires-Dist: djangorestframework (>=3.3)
Requires-Dist: pygal (>=2.0.7)
Requires-Dist: lxml
Requires-Dist: CairoSVG
Requires-Dist: tinycss
Requires-Dist: cssselect
